{"chunk_definitions":[{"row":143,"row_count":1,"visible":true,"expansion_state":0,"options":{"engine":"r","label":"lcagof2","cache":true,"include":false},"document_id":"F4FCCFDA","chunk_id":"cxz9n5tdy2amu","chunk_label":"lcagof"},{"row":162,"row_count":1,"visible":true,"expansion_state":0,"options":{"engine":"r","label":"mglca2","include":false},"document_id":"F4FCCFDA","chunk_id":"cbylga08unt6t","chunk_label":"mglca"},{"row":219,"row_count":1,"visible":true,"expansion_state":0,"options":{"engine":"r","label":"mglca2","include":false},"document_id":"0D1E858A","chunk_id":"cpmbnafedut2j","chunk_label":"lcas"},{"row":235,"row_count":1,"visible":true,"expansion_state":0,"options":{"engine":"r","label":"mglca2","include":false},"document_id":"0D1E858A","chunk_id":"ck6tljiu6n3ha","chunk_label":"mlca"}],"doc_write_time":1630442837}